spsa/__init__.py
spsa/_defaults.py
spsa/_spsa.py
spsa/_utils.py
spsa/iterator.py
spsa/aio/__init__.py
spsa/aio/_aio.py
spsa/aio/iterator.py
spsa/amp/__init__.py
spsa/amp/_amp.py
spsa/amp/iterator.py
spsa/random/__init__.py
spsa/random/iterator.py
spsa-0.1.2.dist-info/LICENSE
spsa-0.1.2.dist-info/METADATA
spsa-0.1.2.dist-info/WHEEL
spsa-0.1.2.dist-info/top_level.txt
spsa-0.1.2.dist-info/RECORD
