Metadata-Version: 2.1
Name: spsa
Version: 0.1.2
Summary: The purpose of this package is to provide multivariable optimizers using SPSA.
Home-page: https://github.com/SimpleArt/spsa
Author: Jack Nguyen
Author-email: jackyeenguyen@gmail.com
License: UNKNOWN
Platform: UNKNOWN
Classifier: Programming Language :: Python :: 3
Classifier: License :: OSI Approved :: MIT License
Classifier: Operating System :: OS Independent
Requires-Python: >=3.5
License-File: LICENSE
